Metadata-Version: 1.0
Name: epidemic-dynamics
Version: 1.2.1
Summary: SIR model
Home-page: UNKNOWN
Author: UNKNOWN
Author-email: UNKNOWN
License: UNKNOWN
Platform: UNKNOWN
